iutility/__init__.py
iutility/__main__.py
iutility/clean/__init__.py
iutility/clean/apt.py
iutility/clean/brew.py
iutility/clean/cache.py
iutility/clean/command.py
iutility/clean/npm.py
iutility/clean/pip.py
iutility/clean/shell.py
iutility/clean/tldr.py
iutility/clean/tmp.py
iutility/git/__init__.py
iutility/git/command.py
iutility/git/define.py
iutility/git/init.py
iutility/git/reset.py
iutility/git/secret.py
iutility/key/__init__.py
iutility/key/_import.py
iutility/key/command.py
iutility/key/define.py
iutility/key/export.py
iutility/update/__init__.py
iutility/update/apt.py
iutility/update/brew.py
iutility/update/command.py
iutility/update/snap.py
iutility/update/tldr.py
iutility-0.0.3.dist-info/WHEEL
iutility-0.0.3.dist-info/LICENSE
iutility-0.0.3.dist-info/METADATA
iutility-0.0.3.dist-info/RECORD
