Metadata-Version: 2.1
Name: iutility
Version: 0.0.3
Summary: My Utils
Home-page: https://liblaf.github.io/iutility/
License: MIT
Author: Qin Li
Author-email: liblaf@outlook.com
Requires-Python: >=3.10,<3.12
Classifier: License :: OSI Approved :: MIT License
Classifier: Programming Language :: Python :: 3
Classifier: Programming Language :: Python :: 3.10
Classifier: Programming Language :: Python :: 3.11
Requires-Dist: click (>=8.1.3,<9.0.0)
Requires-Dist: ishutils (>=0.0.3,<0.0.4)
Requires-Dist: toml-sort (>=0.20.1,<0.21.0)
Requires-Dist: tomlkit (>=0.11.6,<0.12.0)
Project-URL: Documentation, https://liblaf.github.io/iutility/
Project-URL: Repository, https://github.com/liblaf/iutility
